zalando_turnstile/__init__.py
zalando_turnstile-2.0.dist-info/METADATA
zalando_turnstile-2.0.dist-info/DESCRIPTION.rst
zalando_turnstile-2.0.dist-info/metadata.json
zalando_turnstile-2.0.dist-info/WHEEL
zalando_turnstile-2.0.dist-info/RECORD
zalando_turnstile-2.0.dist-info/top_level.txt
