Metadata-Version: 2.0
Name: zalando-turnstile
Version: 2.0
Summary: Turnstile - Zalando Local Git Hooks (META PACKAGE)
Home-page: https://github.com/zalando/turnstile-zalando
Author: Zalando SE
Author-email: UNKNOWN
License: Apache License Version 2.0
Platform: UNKNOWN
Classifier: Programming Language :: Python
Classifier: Programming Language :: Python :: 2.7
Classifier: Programming Language :: Python :: 3.4
Classifier: Development Status :: 4 - Beta
Classifier: Intended Audience :: Developers
Classifier: Operating System :: OS Independent
Classifier: Topic :: Software Development :: Version Control
Requires-Dist: turnstile-core
Requires-Dist: turnstile-codevalidator
